<?xml version="1.0" encoding="utf-8"?>
<ArrayOfSale xmlns:xsi="http://www.w3.org/2001/XMLSchema-instance" xmlns:xsd="http://www.w3.org/2001/XMLSchema">
  <Sale>
    <codeIndex>0</codeIndex>
    <ProductId>1020</ProductId>
    <MinAmount>2</MinAmount>
    <Price>45</Price>
    <Club>true</Club>
    <StartSaleDate>2025-05-06T09:33:23.4817436+03:00</StartSaleDate>
    <EndSaleDate>2025-05-12T09:33:23.4841032+03:00</EndSaleDate>
  </Sale>
  <Sale>
    <codeIndex>0</codeIndex>
    <ProductId>1100</ProductId>
    <MinAmount>1</MinAmount>
    <Price>20</Price>
    <Club>false</Club>
    <StartSaleDate>2025-05-05T09:33:23.5087935+03:00</StartSaleDate>
    <EndSaleDate>2025-05-19T09:33:23.5087958+03:00</EndSaleDate>
  </Sale>
  <Sale>
    <codeIndex>0</codeIndex>
    <ProductId>1160</ProductId>
    <MinAmount>3</MinAmount>
    <Price>55</Price>
    <Club>true</Club>
    <StartSaleDate>2025-05-06T09:33:23.5224407+03:00</StartSaleDate>
    <EndSaleDate>2025-05-09T09:33:23.5224426+03:00</EndSaleDate>
  </Sale>
</ArrayOfSale>